feedbax/__init__.py
feedbax/_io.py
feedbax/_mapping.py
feedbax/_model.py
feedbax/_staged.py
feedbax/_tree.py
feedbax/bodies.py
feedbax/channel.py
feedbax/dimred.py
feedbax/dynamics.py
feedbax/intervene.py
feedbax/iterate.py
feedbax/loss.py
feedbax/misc.py
feedbax/nn.py
feedbax/plot.py
feedbax/state.py
feedbax/task.py
feedbax/train.py
feedbax-0.1.2.dist-info/LICENSE
feedbax-0.1.2.dist-info/METADATA
feedbax-0.1.2.dist-info/WHEEL
feedbax-0.1.2.dist-info/top_level.txt
feedbax-0.1.2.dist-info/RECORD
