Metadata-Version: 2.1
Name: feedbax
Version: 0.1.2
Summary: Optimal feedback control + interventions in JAX.
Author-email: Matt L Laporte <matt.l.laporte@gmail.com>
License: Apache License
Project-URL: repository, https://github.com/mlprt/feedbax
Keywords: jax,neural-networks,optimal-control,optimal-feedback-control,pytorch,biomechanics
Classifier: Development Status :: 3 - Alpha
Classifier: Intended Audience :: Developers
Classifier: Intended Audience :: Science/Research
Classifier: License :: OSI Approved :: Apache Software License
Classifier: Natural Language :: English
Classifier: Programming Language :: Python
Classifier: Programming Language :: Python :: 3
Classifier: Programming Language :: Python :: 3 :: Only
Classifier: Programming Language :: Python :: 3.11
Classifier: Programming Language :: Python :: 3.12
Requires-Python: >=3.11
License-File: LICENSE
Requires-Dist: diffrax
Requires-Dist: equinox
Requires-Dist: jax
Requires-Dist: jaxtyping
Requires-Dist: matplotlib
Requires-Dist: numpy
Requires-Dist: optax
Requires-Dist: seaborn
Requires-Dist: tqdm
Requires-Dist: tensorboardX
Provides-Extra: analysis
Requires-Dist: pandas ; extra == 'analysis'
Provides-Extra: tensorboard
Requires-Dist: tensorboardX ; extra == 'tensorboard'
Requires-Dist: crc32c ; extra == 'tensorboard'
Provides-Extra: tests
Requires-Dist: coverage ; extra == 'tests'
Requires-Dist: pytest ; extra == 'tests'
Provides-Extra: typing
Requires-Dist: pyright ; extra == 'typing'
Requires-Dist: typeguard ; extra == 'typing'
